{"type":"FeatureCollection", "features": [
{"type":"Feature","geometry":{"type":"Point","coordinates":[83.9773385,28.2572426]},"properties":{"Amenities":"Bank","Name":"Lumbini bikas bank ltd","Opening_Ti":"10:00:00.000+05:45","Closing_Ti":"17:00:00.000+05:45","Contact_No":0,"_Locaton_l":28.2572426,"_Locaton_1":83.9773385}},
{"type":"Feature","geometry":{"type":"Point","coordinates":[83.9725433,28.2609439]},"properties":{"Amenities":"Bank","Name":"Prime bank ltd","Opening_Ti":"10:00:00.000+05:45","Closing_Ti":"16:00:00.000+05:45","Contact_No":6144416,"_Locaton_l":28.2609439,"_Locaton_1":83.9725433}},
{"type":"Feature","geometry":{"type":"Point","coordinates":[83.9721771,28.2616779]},"properties":{"Amenities":"Bank","Name":"Machhapuchhre Bank","Opening_Ti":"10:00:00.000+05:45","Closing_Ti":"15:00:00.000+05:45","Contact_No":97715970555,"_Locaton_l":28.2616779,"_Locaton_1":83.9721771}},
{"type":"Feature","geometry":{"type":"Point","coordinates":[83.9716701,28.260842]},"properties":{"Amenities":"Bank","Name":"NIMB Ltd","Opening_Ti":"09:00:00.000+05:45","Closing_Ti":"16:00:00.000+05:45","Contact_No":0,"_Locaton_l":28.260842,"_Locaton_1":83.9716701}},
{"type":"Feature","geometry":{"type":"Point","coordinates":[83.9723997,28.2613548]},"properties":{"Amenities":"Bank","Name":"Muktinath Bikas Bank","Opening_Ti":"10:00:00.000+05:45","Closing_Ti":"16:00:00.000+05:45","Contact_No":61445331,"_Locaton_l":28.2613548,"_Locaton_1":83.9723997}},
{"type":"Feature","geometry":{"type":"Point","coordinates":[83.972896,28.2611489]},"properties":{"Amenities":"Bank","Name":"Himalayan Bank Limited","Opening_Ti":"10:00:00.000+05:45","Closing_Ti":"16:00:00.000+05:45","Contact_No":61443430,"_Locaton_l":28.2611489,"_Locaton_1":83.972896}},
{"type":"Feature","geometry":{"type":"Point","coordinates":[83.9797296,28.2633318]},"properties":{"Amenities":"Bank","Name":"Garima Bikas Bank","Opening_Ti":"10:00:00.000+05:45","Closing_Ti":"16:00:00.000+05:45","Contact_No":0,"_Locaton_l":28.2633318,"_Locaton_1":83.9797296}},
{"type":"Feature","geometry":{"type":"Point","coordinates":[83.9786651,28.2554831]},"properties":{"Amenities":"Bank","Name":"NIC Asia bank Ltd","Opening_Ti":"10:00:00.000+05:45","Closing_Ti":"16:00:00.000+05:45","Contact_No":0,"_Locaton_l":28.2554831,"_Locaton_1":83.9786651}},
{"type":"Feature","geometry":{"type":"Point","coordinates":[83.9867831,28.248605]},"properties":{"Amenities":"Bank","Name":"Kamana sewa bikash bank","Opening_Ti":"10:00:00.000+05:45","Closing_Ti":"16:00:00.000+05:45","Contact_No":61444600,"_Locaton_l":28.248605,"_Locaton_1":83.9867831}}
]}